taskguard/__init__.py
taskguard/best_practices.py
taskguard/cli.py
taskguard/core/__init__.py
taskguard/core/controller.py
taskguard/core/project.py
taskguard/core/task.py
taskguard/document_parser.py
taskguard/llm/__init__.py
taskguard/llm/interface.py
taskguard/llm/providers.py
taskguard/local_llm_interface.py
taskguard/security/__init__.py
taskguard/security/patterns.py
taskguard/security/scanner.py
taskguard/security/validator.py
taskguard/shell_integration.py
taskguard/taskguard.py
taskguard-0.2.3.dist-info/LICENSE
taskguard-0.2.3.dist-info/METADATA
taskguard-0.2.3.dist-info/WHEEL
taskguard-0.2.3.dist-info/entry_points.txt
taskguard-0.2.3.dist-info/RECORD
