Metadata-Version: 2.3
Name: taskguard
Version: 0.2.3
Summary: LLM Task Controller - Intelligent project management with local AI
License: Apache-2.0
Author: Tom Sapletta
Author-email: info@softreck.dev
Maintainer: WRONAI Team
Requires-Python: >=3.8,<4.0
Classifier: Development Status :: 4 - Beta
Classifier: Environment :: Console
Classifier: Intended Audience :: Developers
Classifier: License :: OSI Approved :: Apache Software License
Classifier: Natural Language :: English
Classifier: Operating System :: OS Independent
Classifier: Programming Language :: Python :: 3
Classifier: Programming Language :: Python :: 3.8
Classifier: Programming Language :: Python :: 3.9
Classifier: Programming Language :: Python :: 3.10
Classifier: Programming Language :: Python :: 3.11
Classifier: Programming Language :: Python :: 3.12
Classifier: Programming Language :: Python :: 3.13
Classifier: Topic :: Office/Business :: Scheduling
Classifier: Topic :: Scientific/Engineering :: Artificial Intelligence
Classifier: Topic :: Software Development :: Quality Assurance
Requires-Dist: pyyaml (>=6.0,<7.0)
Requires-Dist: requests (>=2.31.0,<3.0.0)
Requires-Dist: typing-extensions (>=4.7.1,<5.0.0) ; python_version < "3.8"
Project-URL: Bug Tracker, https://github.com/wronai/taskguard/issues
Project-URL: Changelog, https://github.com/wronai/taskguard/blob/main/CHANGELOG.md
Project-URL: Documentation, https://taskguard.readthedocs.io
Project-URL: Homepage, https://github.com/wronai/taskguard
Project-URL: Repository, https://github.com/wronai/taskguard.git
